dicn/__init__.py
dicn/dicn.py
dicn-0.1.0.dist-info/LICENSE
dicn-0.1.0.dist-info/METADATA
dicn-0.1.0.dist-info/WHEEL
dicn-0.1.0.dist-info/top_level.txt
dicn-0.1.0.dist-info/RECORD
