Metadata-Version: 2.1
Name: dicn
Version: 0.1.0
Summary: An implementation of the Direct-Indirect Common Neighbors algorithm
Home-page: https://github.com/jlb52/direct-indirect-common-neighbors
Author: Jackson Burke
License-File: LICENSE
Requires-Dist: networkx
Requires-Dist: numpy
